sunrpc/__init__.py
sunrpc/client.py
sunrpc/portmapper.py
sunrpc/proxy.py
sunrpc/server.py
sunrpc/services.py
sunrpc/sunrpc.py
sunrpc/types.py
sunrpc/utils.py
sunrpc-1.1.0.dist-info/LICENSE
sunrpc-1.1.0.dist-info/METADATA
sunrpc-1.1.0.dist-info/WHEEL
sunrpc-1.1.0.dist-info/top_level.txt
sunrpc-1.1.0.dist-info/RECORD
