Metadata-Version: 2.1
Name: sunrpc
Version: 1.1.0
Summary: sunrpc implements remote procedure calls according to RFC1057
Author: Tobias Neitzel (@qtc_de)
License: GNU GENERAL PUBLIC LICENSE
Project-URL: Homepage, https://github.com/usdAG/sunrpc
Project-URL: Bug Tracker, https://github.com/usdAG/sunrpc/issues
Classifier: Programming Language :: Python :: 3
Classifier: License :: OSI Approved :: GNU General Public License v3 (GPLv3)
Classifier: Operating System :: OS Independent
Requires-Python: >=3.9
License-File: LICENSE
